{
  "updated_at": 1779879769,
  "updated": "2026-05-27 16:32:49",
  "window_days": 90,
  "samples": [
    {
      "generated_at": 1779801696,
      "last_seen_utc": "2026-05-26T13:21:36Z",
      "overall": "ok",
      "ok": 16,
      "warn": 0,
      "fail": 0
    },
    {
      "generated_at": 1779801785,
      "last_seen_utc": "2026-05-26T13:23:05Z",
      "overall": "ok",
      "ok": 16,
      "warn": 0,
      "fail": 0
    },
    {
      "generated_at": 1779802388,
      "last_seen_utc": "2026-05-26T13:33:08Z",
      "overall": "ok",
      "ok": 16,
      "warn": 0,
      "fail": 0
    },
    {
      "generated_at": 1779802991,
      "last_seen_utc": "2026-05-26T13:43:11Z",
      "overall": "ok",
      "ok": 16,
      "warn": 0,
      "fail": 0
    },
    {
      "generated_at": 1779803593,
      "last_seen_utc": "2026-05-26T13:53:13Z",
      "overall": "ok",
      "ok": 16,
      "warn": 0,
      "fail": 0
    },
    {
      "generated_at": 1779804196,
      "last_seen_utc": "2026-05-26T14:03:16Z",
      "overall": "ok",
      "ok": 16,
      "warn": 0,
      "fail": 0
    },
    {
      "generated_at": 1779804817,
      "last_seen_utc": "2026-05-26T14:13:37Z",
      "overall": "ok",
      "ok": 16,
      "warn": 0,
      "fail": 0
    },
    {
      "generated_at": 1779805420,
      "last_seen_utc": "2026-05-26T14:23:40Z",
      "overall": "ok",
      "ok": 16,
      "warn": 0,
      "fail": 0
    },
    {
      "generated_at": 1779806022,
      "last_seen_utc": "2026-05-26T14:33:42Z",
      "overall": "ok",
      "ok": 16,
      "warn": 0,
      "fail": 0
    },
    {
      "generated_at": 1779806625,
      "last_seen_utc": "2026-05-26T14:43:45Z",
      "overall": "ok",
      "ok": 16,
      "warn": 0,
      "fail": 0
    },
    {
      "generated_at": 1779807227,
      "last_seen_utc": "2026-05-26T14:53:47Z",
      "overall": "ok",
      "ok": 16,
      "warn": 0,
      "fail": 0
    },
    {
      "generated_at": 1779807830,
      "last_seen_utc": "2026-05-26T15:03:50Z",
      "overall": "ok",
      "ok": 16,
      "warn": 0,
      "fail": 0
    },
    {
      "generated_at": 1779808432,
      "last_seen_utc": "2026-05-26T15:13:52Z",
      "overall": "ok",
      "ok": 16,
      "warn": 0,
      "fail": 0
    },
    {
      "generated_at": 1779809035,
      "last_seen_utc": "2026-05-26T15:23:55Z",
      "overall": "ok",
      "ok": 16,
      "warn": 0,
      "fail": 0
    },
    {
      "generated_at": 1779809637,
      "last_seen_utc": "2026-05-26T15:33:57Z",
      "overall": "ok",
      "ok": 16,
      "warn": 0,
      "fail": 0
    },
    {
      "generated_at": 1779810240,
      "last_seen_utc": "2026-05-26T15:44:00Z",
      "overall": "ok",
      "ok": 16,
      "warn": 0,
      "fail": 0
    },
    {
      "generated_at": 1779810843,
      "last_seen_utc": "2026-05-26T15:54:03Z",
      "overall": "ok",
      "ok": 16,
      "warn": 0,
      "fail": 0
    },
    {
      "generated_at": 1779811445,
      "last_seen_utc": "2026-05-26T16:04:05Z",
      "overall": "ok",
      "ok": 16,
      "warn": 0,
      "fail": 0
    },
    {
      "generated_at": 1779812047,
      "last_seen_utc": "2026-05-26T16:14:07Z",
      "overall": "ok",
      "ok": 16,
      "warn": 0,
      "fail": 0
    },
    {
      "generated_at": 1779812650,
      "last_seen_utc": "2026-05-26T16:24:10Z",
      "overall": "ok",
      "ok": 16,
      "warn": 0,
      "fail": 0
    },
    {
      "generated_at": 1779813252,
      "last_seen_utc": "2026-05-26T16:34:12Z",
      "overall": "ok",
      "ok": 16,
      "warn": 0,
      "fail": 0
    },
    {
      "generated_at": 1779813854,
      "last_seen_utc": "2026-05-26T16:44:14Z",
      "overall": "ok",
      "ok": 16,
      "warn": 0,
      "fail": 0
    },
    {
      "generated_at": 1779814457,
      "last_seen_utc": "2026-05-26T16:54:17Z",
      "overall": "ok",
      "ok": 16,
      "warn": 0,
      "fail": 0
    },
    {
      "generated_at": 1779815059,
      "last_seen_utc": "2026-05-26T17:04:19Z",
      "overall": "ok",
      "ok": 16,
      "warn": 0,
      "fail": 0
    },
    {
      "generated_at": 1779815662,
      "last_seen_utc": "2026-05-26T17:14:22Z",
      "overall": "fail",
      "ok": 15,
      "warn": 0,
      "fail": 1
    },
    {
      "generated_at": 1779816265,
      "last_seen_utc": "2026-05-26T17:24:25Z",
      "overall": "fail",
      "ok": 15,
      "warn": 0,
      "fail": 1
    },
    {
      "generated_at": 1779816867,
      "last_seen_utc": "2026-05-26T17:34:27Z",
      "overall": "fail",
      "ok": 15,
      "warn": 0,
      "fail": 1
    },
    {
      "generated_at": 1779817470,
      "last_seen_utc": "2026-05-26T17:44:30Z",
      "overall": "fail",
      "ok": 15,
      "warn": 0,
      "fail": 1
    },
    {
      "generated_at": 1779818072,
      "last_seen_utc": "2026-05-26T17:54:32Z",
      "overall": "fail",
      "ok": 15,
      "warn": 0,
      "fail": 1
    },
    {
      "generated_at": 1779818675,
      "last_seen_utc": "2026-05-26T18:04:35Z",
      "overall": "fail",
      "ok": 15,
      "warn": 0,
      "fail": 1
    },
    {
      "generated_at": 1779819277,
      "last_seen_utc": "2026-05-26T18:14:37Z",
      "overall": "fail",
      "ok": 15,
      "warn": 0,
      "fail": 1
    },
    {
      "generated_at": 1779819880,
      "last_seen_utc": "2026-05-26T18:24:40Z",
      "overall": "fail",
      "ok": 15,
      "warn": 0,
      "fail": 1
    },
    {
      "generated_at": 1779820482,
      "last_seen_utc": "2026-05-26T18:34:42Z",
      "overall": "fail",
      "ok": 15,
      "warn": 0,
      "fail": 1
    },
    {
      "generated_at": 1779821084,
      "last_seen_utc": "2026-05-26T18:44:44Z",
      "overall": "fail",
      "ok": 15,
      "warn": 0,
      "fail": 1
    },
    {
      "generated_at": 1779821686,
      "last_seen_utc": "2026-05-26T18:54:46Z",
      "overall": "fail",
      "ok": 15,
      "warn": 0,
      "fail": 1
    },
    {
      "generated_at": 1779822289,
      "last_seen_utc": "2026-05-26T19:04:49Z",
      "overall": "fail",
      "ok": 15,
      "warn": 0,
      "fail": 1
    },
    {
      "generated_at": 1779822891,
      "last_seen_utc": "2026-05-26T19:14:51Z",
      "overall": "fail",
      "ok": 15,
      "warn": 0,
      "fail": 1
    },
    {
      "generated_at": 1779823494,
      "last_seen_utc": "2026-05-26T19:24:54Z",
      "overall": "fail",
      "ok": 15,
      "warn": 0,
      "fail": 1
    },
    {
      "generated_at": 1779824097,
      "last_seen_utc": "2026-05-26T19:34:57Z",
      "overall": "fail",
      "ok": 15,
      "warn": 0,
      "fail": 1
    },
    {
      "generated_at": 1779824699,
      "last_seen_utc": "2026-05-26T19:44:59Z",
      "overall": "fail",
      "ok": 15,
      "warn": 0,
      "fail": 1
    },
    {
      "generated_at": 1779825302,
      "last_seen_utc": "2026-05-26T19:55:02Z",
      "overall": "fail",
      "ok": 15,
      "warn": 0,
      "fail": 1
    },
    {
      "generated_at": 1779825904,
      "last_seen_utc": "2026-05-26T20:05:04Z",
      "overall": "fail",
      "ok": 15,
      "warn": 0,
      "fail": 1
    },
    {
      "generated_at": 1779826506,
      "last_seen_utc": "2026-05-26T20:15:06Z",
      "overall": "fail",
      "ok": 15,
      "warn": 0,
      "fail": 1
    },
    {
      "generated_at": 1779827108,
      "last_seen_utc": "2026-05-26T20:25:08Z",
      "overall": "fail",
      "ok": 15,
      "warn": 0,
      "fail": 1
    },
    {
      "generated_at": 1779827293,
      "last_seen_utc": "2026-05-26T20:28:13Z",
      "overall": "ok",
      "ok": 16,
      "warn": 0,
      "fail": 0
    },
    {
      "generated_at": 1779834619,
      "last_seen_utc": "2026-05-26T22:30:19Z",
      "overall": "ok",
      "ok": 16,
      "warn": 0,
      "fail": 0
    },
    {
      "generated_at": 1779846117,
      "last_seen_utc": "2026-05-27T01:41:57Z",
      "overall": "ok",
      "ok": 16,
      "warn": 0,
      "fail": 0
    },
    {
      "generated_at": 1779857362,
      "last_seen_utc": "2026-05-27T04:49:22Z",
      "overall": "ok",
      "ok": 16,
      "warn": 0,
      "fail": 0
    },
    {
      "generated_at": 1779859272,
      "last_seen_utc": "2026-05-27T05:21:12Z",
      "overall": "ok",
      "ok": 16,
      "warn": 0,
      "fail": 0
    },
    {
      "generated_at": 1779859874,
      "last_seen_utc": "2026-05-27T05:31:14Z",
      "overall": "ok",
      "ok": 16,
      "warn": 0,
      "fail": 0
    },
    {
      "generated_at": 1779860477,
      "last_seen_utc": "2026-05-27T05:41:17Z",
      "overall": "ok",
      "ok": 16,
      "warn": 0,
      "fail": 0
    },
    {
      "generated_at": 1779861079,
      "last_seen_utc": "2026-05-27T05:51:19Z",
      "overall": "ok",
      "ok": 16,
      "warn": 0,
      "fail": 0
    },
    {
      "generated_at": 1779861681,
      "last_seen_utc": "2026-05-27T06:01:21Z",
      "overall": "ok",
      "ok": 16,
      "warn": 0,
      "fail": 0
    },
    {
      "generated_at": 1779862284,
      "last_seen_utc": "2026-05-27T06:11:24Z",
      "overall": "ok",
      "ok": 16,
      "warn": 0,
      "fail": 0
    },
    {
      "generated_at": 1779862886,
      "last_seen_utc": "2026-05-27T06:21:26Z",
      "overall": "ok",
      "ok": 16,
      "warn": 0,
      "fail": 0
    },
    {
      "generated_at": 1779863488,
      "last_seen_utc": "2026-05-27T06:31:28Z",
      "overall": "ok",
      "ok": 16,
      "warn": 0,
      "fail": 0
    },
    {
      "generated_at": 1779864091,
      "last_seen_utc": "2026-05-27T06:41:31Z",
      "overall": "ok",
      "ok": 16,
      "warn": 0,
      "fail": 0
    },
    {
      "generated_at": 1779864694,
      "last_seen_utc": "2026-05-27T06:51:34Z",
      "overall": "ok",
      "ok": 16,
      "warn": 0,
      "fail": 0
    },
    {
      "generated_at": 1779865296,
      "last_seen_utc": "2026-05-27T07:01:36Z",
      "overall": "ok",
      "ok": 16,
      "warn": 0,
      "fail": 0
    },
    {
      "generated_at": 1779865898,
      "last_seen_utc": "2026-05-27T07:11:38Z",
      "overall": "ok",
      "ok": 16,
      "warn": 0,
      "fail": 0
    },
    {
      "generated_at": 1779866500,
      "last_seen_utc": "2026-05-27T07:21:40Z",
      "overall": "ok",
      "ok": 16,
      "warn": 0,
      "fail": 0
    },
    {
      "generated_at": 1779867103,
      "last_seen_utc": "2026-05-27T07:31:43Z",
      "overall": "ok",
      "ok": 16,
      "warn": 0,
      "fail": 0
    },
    {
      "generated_at": 1779867705,
      "last_seen_utc": "2026-05-27T07:41:45Z",
      "overall": "ok",
      "ok": 16,
      "warn": 0,
      "fail": 0
    },
    {
      "generated_at": 1779868307,
      "last_seen_utc": "2026-05-27T07:51:47Z",
      "overall": "ok",
      "ok": 16,
      "warn": 0,
      "fail": 0
    },
    {
      "generated_at": 1779868910,
      "last_seen_utc": "2026-05-27T08:01:50Z",
      "overall": "ok",
      "ok": 16,
      "warn": 0,
      "fail": 0
    },
    {
      "generated_at": 1779869512,
      "last_seen_utc": "2026-05-27T08:11:52Z",
      "overall": "ok",
      "ok": 16,
      "warn": 0,
      "fail": 0
    },
    {
      "generated_at": 1779870115,
      "last_seen_utc": "2026-05-27T08:21:55Z",
      "overall": "ok",
      "ok": 16,
      "warn": 0,
      "fail": 0
    },
    {
      "generated_at": 1779870717,
      "last_seen_utc": "2026-05-27T08:31:57Z",
      "overall": "ok",
      "ok": 16,
      "warn": 0,
      "fail": 0
    },
    {
      "generated_at": 1779871320,
      "last_seen_utc": "2026-05-27T08:42:00Z",
      "overall": "ok",
      "ok": 16,
      "warn": 0,
      "fail": 0
    },
    {
      "generated_at": 1779871922,
      "last_seen_utc": "2026-05-27T08:52:02Z",
      "overall": "ok",
      "ok": 16,
      "warn": 0,
      "fail": 0
    },
    {
      "generated_at": 1779872526,
      "last_seen_utc": "2026-05-27T09:02:06Z",
      "overall": "ok",
      "ok": 16,
      "warn": 0,
      "fail": 0
    },
    {
      "generated_at": 1779873136,
      "last_seen_utc": "2026-05-27T09:12:16Z",
      "overall": "ok",
      "ok": 16,
      "warn": 0,
      "fail": 0
    },
    {
      "generated_at": 1779873742,
      "last_seen_utc": "2026-05-27T09:22:22Z",
      "overall": "ok",
      "ok": 16,
      "warn": 0,
      "fail": 0
    },
    {
      "generated_at": 1779874345,
      "last_seen_utc": "2026-05-27T09:32:25Z",
      "overall": "ok",
      "ok": 16,
      "warn": 0,
      "fail": 0
    },
    {
      "generated_at": 1779874948,
      "last_seen_utc": "2026-05-27T09:42:28Z",
      "overall": "ok",
      "ok": 16,
      "warn": 0,
      "fail": 0
    },
    {
      "generated_at": 1779875550,
      "last_seen_utc": "2026-05-27T09:52:30Z",
      "overall": "ok",
      "ok": 16,
      "warn": 0,
      "fail": 0
    },
    {
      "generated_at": 1779876153,
      "last_seen_utc": "2026-05-27T10:02:33Z",
      "overall": "ok",
      "ok": 16,
      "warn": 0,
      "fail": 0
    },
    {
      "generated_at": 1779876756,
      "last_seen_utc": "2026-05-27T10:12:36Z",
      "overall": "ok",
      "ok": 16,
      "warn": 0,
      "fail": 0
    },
    {
      "generated_at": 1779877358,
      "last_seen_utc": "2026-05-27T10:22:38Z",
      "overall": "ok",
      "ok": 16,
      "warn": 0,
      "fail": 0
    },
    {
      "generated_at": 1779877961,
      "last_seen_utc": "2026-05-27T10:32:41Z",
      "overall": "ok",
      "ok": 16,
      "warn": 0,
      "fail": 0
    },
    {
      "generated_at": 1779878564,
      "last_seen_utc": "2026-05-27T10:42:44Z",
      "overall": "ok",
      "ok": 16,
      "warn": 0,
      "fail": 0
    },
    {
      "generated_at": 1779879167,
      "last_seen_utc": "2026-05-27T10:52:47Z",
      "overall": "ok",
      "ok": 16,
      "warn": 0,
      "fail": 0
    },
    {
      "generated_at": 1779879769,
      "last_seen_utc": "2026-05-27T11:02:49Z",
      "overall": "ok",
      "ok": 16,
      "warn": 0,
      "fail": 0
    }
  ],
  "days": [
    {
      "date": "2026-04-23",
      "status": "empty",
      "samples": 0,
      "ok_samples": 0,
      "warn_samples": 0,
      "fail_samples": 0,
      "uptime_pct": 0
    },
    {
      "date": "2026-04-24",
      "status": "empty",
      "samples": 0,
      "ok_samples": 0,
      "warn_samples": 0,
      "fail_samples": 0,
      "uptime_pct": 0
    },
    {
      "date": "2026-04-25",
      "status": "empty",
      "samples": 0,
      "ok_samples": 0,
      "warn_samples": 0,
      "fail_samples": 0,
      "uptime_pct": 0
    },
    {
      "date": "2026-04-26",
      "status": "empty",
      "samples": 0,
      "ok_samples": 0,
      "warn_samples": 0,
      "fail_samples": 0,
      "uptime_pct": 0
    },
    {
      "date": "2026-04-27",
      "status": "empty",
      "samples": 0,
      "ok_samples": 0,
      "warn_samples": 0,
      "fail_samples": 0,
      "uptime_pct": 0
    },
    {
      "date": "2026-04-28",
      "status": "empty",
      "samples": 0,
      "ok_samples": 0,
      "warn_samples": 0,
      "fail_samples": 0,
      "uptime_pct": 0
    },
    {
      "date": "2026-04-29",
      "status": "empty",
      "samples": 0,
      "ok_samples": 0,
      "warn_samples": 0,
      "fail_samples": 0,
      "uptime_pct": 0
    },
    {
      "date": "2026-04-30",
      "status": "empty",
      "samples": 0,
      "ok_samples": 0,
      "warn_samples": 0,
      "fail_samples": 0,
      "uptime_pct": 0
    },
    {
      "date": "2026-05-01",
      "status": "empty",
      "samples": 0,
      "ok_samples": 0,
      "warn_samples": 0,
      "fail_samples": 0,
      "uptime_pct": 0
    },
    {
      "date": "2026-05-02",
      "status": "empty",
      "samples": 0,
      "ok_samples": 0,
      "warn_samples": 0,
      "fail_samples": 0,
      "uptime_pct": 0
    },
    {
      "date": "2026-05-03",
      "status": "empty",
      "samples": 0,
      "ok_samples": 0,
      "warn_samples": 0,
      "fail_samples": 0,
      "uptime_pct": 0
    },
    {
      "date": "2026-05-04",
      "status": "empty",
      "samples": 0,
      "ok_samples": 0,
      "warn_samples": 0,
      "fail_samples": 0,
      "uptime_pct": 0
    },
    {
      "date": "2026-05-05",
      "status": "empty",
      "samples": 0,
      "ok_samples": 0,
      "warn_samples": 0,
      "fail_samples": 0,
      "uptime_pct": 0
    },
    {
      "date": "2026-05-06",
      "status": "empty",
      "samples": 0,
      "ok_samples": 0,
      "warn_samples": 0,
      "fail_samples": 0,
      "uptime_pct": 0
    },
    {
      "date": "2026-05-07",
      "status": "empty",
      "samples": 0,
      "ok_samples": 0,
      "warn_samples": 0,
      "fail_samples": 0,
      "uptime_pct": 0
    },
    {
      "date": "2026-05-08",
      "status": "empty",
      "samples": 0,
      "ok_samples": 0,
      "warn_samples": 0,
      "fail_samples": 0,
      "uptime_pct": 0
    },
    {
      "date": "2026-05-09",
      "status": "empty",
      "samples": 0,
      "ok_samples": 0,
      "warn_samples": 0,
      "fail_samples": 0,
      "uptime_pct": 0
    },
    {
      "date": "2026-05-10",
      "status": "empty",
      "samples": 0,
      "ok_samples": 0,
      "warn_samples": 0,
      "fail_samples": 0,
      "uptime_pct": 0
    },
    {
      "date": "2026-05-11",
      "status": "empty",
      "samples": 0,
      "ok_samples": 0,
      "warn_samples": 0,
      "fail_samples": 0,
      "uptime_pct": 0
    },
    {
      "date": "2026-05-12",
      "status": "empty",
      "samples": 0,
      "ok_samples": 0,
      "warn_samples": 0,
      "fail_samples": 0,
      "uptime_pct": 0
    },
    {
      "date": "2026-05-13",
      "status": "empty",
      "samples": 0,
      "ok_samples": 0,
      "warn_samples": 0,
      "fail_samples": 0,
      "uptime_pct": 0
    },
    {
      "date": "2026-05-14",
      "status": "empty",
      "samples": 0,
      "ok_samples": 0,
      "warn_samples": 0,
      "fail_samples": 0,
      "uptime_pct": 0
    },
    {
      "date": "2026-05-15",
      "status": "empty",
      "samples": 0,
      "ok_samples": 0,
      "warn_samples": 0,
      "fail_samples": 0,
      "uptime_pct": 0
    },
    {
      "date": "2026-05-16",
      "status": "empty",
      "samples": 0,
      "ok_samples": 0,
      "warn_samples": 0,
      "fail_samples": 0,
      "uptime_pct": 0
    },
    {
      "date": "2026-05-17",
      "status": "empty",
      "samples": 0,
      "ok_samples": 0,
      "warn_samples": 0,
      "fail_samples": 0,
      "uptime_pct": 0
    },
    {
      "date": "2026-05-18",
      "status": "empty",
      "samples": 0,
      "ok_samples": 0,
      "warn_samples": 0,
      "fail_samples": 0,
      "uptime_pct": 0
    },
    {
      "date": "2026-05-19",
      "status": "empty",
      "samples": 0,
      "ok_samples": 0,
      "warn_samples": 0,
      "fail_samples": 0,
      "uptime_pct": 0
    },
    {
      "date": "2026-05-20",
      "status": "empty",
      "samples": 0,
      "ok_samples": 0,
      "warn_samples": 0,
      "fail_samples": 0,
      "uptime_pct": 0
    },
    {
      "date": "2026-05-21",
      "status": "empty",
      "samples": 0,
      "ok_samples": 0,
      "warn_samples": 0,
      "fail_samples": 0,
      "uptime_pct": 0
    },
    {
      "date": "2026-05-22",
      "status": "empty",
      "samples": 0,
      "ok_samples": 0,
      "warn_samples": 0,
      "fail_samples": 0,
      "uptime_pct": 0
    },
    {
      "date": "2026-05-23",
      "status": "empty",
      "samples": 0,
      "ok_samples": 0,
      "warn_samples": 0,
      "fail_samples": 0,
      "uptime_pct": 0
    },
    {
      "date": "2026-05-24",
      "status": "empty",
      "samples": 0,
      "ok_samples": 0,
      "warn_samples": 0,
      "fail_samples": 0,
      "uptime_pct": 0
    },
    {
      "date": "2026-05-25",
      "status": "empty",
      "samples": 0,
      "ok_samples": 0,
      "warn_samples": 0,
      "fail_samples": 0,
      "uptime_pct": 0
    },
    {
      "date": "2026-05-26",
      "status": "fail",
      "samples": 46,
      "ok_samples": 26,
      "warn_samples": 0,
      "fail_samples": 20,
      "uptime_pct": 56
    },
    {
      "date": "2026-05-27",
      "status": "ok",
      "samples": 37,
      "ok_samples": 37,
      "warn_samples": 0,
      "fail_samples": 0,
      "uptime_pct": 100
    }
  ]
}
